antsibull_docutils/__init__.py
antsibull_docutils/html_utils.py
antsibull_docutils/markdown.py
antsibull_docutils/md_utils.py
antsibull_docutils/py.typed
antsibull_docutils/rst_code_finder.py
antsibull_docutils/rst_utils.py
antsibull_docutils/utils.py
antsibull_docutils-1.4.0.dist-info/METADATA
antsibull_docutils-1.4.0.dist-info/WHEEL
antsibull_docutils-1.4.0.dist-info/licenses/LICENSES/GPL-3.0-or-later.txt
antsibull_docutils-1.4.0.dist-info/RECORD
