Metadata-Version: 2.4
Name: antsibull-docutils
Version: 1.4.0
Summary: Antsibull docutils helpers
Project-URL: Source code, https://github.com/ansible-community/antsibull-docutils/
Project-URL: Code of Conduct, https://docs.ansible.com/projects/ansible/latest/community/code_of_conduct.html
Project-URL: Bug tracker, https://github.com/ansible-community/antsibull-docutils/issues
Project-URL: Changelog, https://github.com/ansible-community/antsibull-docutils/tree/main/CHANGELOG.md
Author-email: Felix Fontein <felix@fontein.de>
Maintainer-email: Felix Fontein <felix@fontein.de>, Maxwell G <maxwell@gtmx.me>
License-Expression: GPL-3.0-or-later
License-File: LICENSES/GPL-3.0-or-later.txt
Classifier: Development Status :: 5 - Production/Stable
Classifier: Framework :: Ansible
Classifier: Intended Audience :: Developers
Classifier: Programming Language :: Python :: 3
Classifier: Programming Language :: Python :: 3.9
Classifier: Programming Language :: Python :: 3.10
Classifier: Programming Language :: Python :: 3.11
Classifier: Programming Language :: Python :: 3.12
Classifier: Programming Language :: Python :: 3.13
Classifier: Programming Language :: Python :: 3.14
Classifier: Typing :: Typed
Requires-Python: >=3.9.0
Requires-Dist: docutils
Provides-Extra: codeqa
Requires-Dist: antsibull-changelog; extra == 'codeqa'
Requires-Dist: flake8>=3.8.0; extra == 'codeqa'
Requires-Dist: pylint; extra == 'codeqa'
Requires-Dist: reuse; extra == 'codeqa'
Provides-Extra: coverage
Requires-Dist: coverage[toml]; extra == 'coverage'
Provides-Extra: dev
Requires-Dist: antsibull-changelog; extra == 'dev'
Requires-Dist: black>=24; extra == 'dev'
Requires-Dist: coverage[toml]; extra == 'dev'
Requires-Dist: flake8>=3.8.0; extra == 'dev'
Requires-Dist: isort; extra == 'dev'
Requires-Dist: mypy; extra == 'dev'
Requires-Dist: nox; extra == 'dev'
Requires-Dist: pylint; extra == 'dev'
Requires-Dist: pytest; extra == 'dev'
Requires-Dist: pytest-cov; extra == 'dev'
Requires-Dist: pytest-error-for-skips; extra == 'dev'
Requires-Dist: reuse; extra == 'dev'
Requires-Dist: types-docutils; extra == 'dev'
Requires-Dist: types-pyyaml; extra == 'dev'
Requires-Dist: types-toml; extra == 'dev'
Provides-Extra: formatters
Requires-Dist: black>=24; extra == 'formatters'
Requires-Dist: isort; extra == 'formatters'
Provides-Extra: test
Requires-Dist: pytest; extra == 'test'
Requires-Dist: pytest-cov; extra == 'test'
Requires-Dist: pytest-error-for-skips; extra == 'test'
Provides-Extra: typing
Requires-Dist: mypy; extra == 'typing'
Requires-Dist: types-docutils; extra == 'typing'
Requires-Dist: types-pyyaml; extra == 'typing'
Requires-Dist: types-toml; extra == 'typing'
